kakao_analyzer/__init__.py
kakao_analyzer/__main__.py
kakao_analyzer/chat_preprocessor.py
kakao_analyzer/config.py
kakao_analyzer/context_topics.py
kakao_analyzer/dataset_optimizer.py
kakao_analyzer/embeddings.py
kakao_analyzer/fun_metrics.py
kakao_analyzer/io_loader.py
kakao_analyzer/mention_analyzer.py
kakao_analyzer/mood_analyzer.py
kakao_analyzer/pipeline.py
kakao_analyzer/report.py
kakao_analyzer/rhythm_analyzer.py
kakao_analyzer/smart_search.py
kakao_analyzer/splade.py
kakao_analyzer/stats_basic.py
kakao_analyzer/topic_sentiment_analyzer.py
kakao_analyzer/turn_splitter.py
kakao_analyzer/utils.py
kakao_analyzer/viz.py
kakao_analyzer-1.0.2.dist-info/licenses/LICENSE
kakao_analyzer-1.0.2.dist-info/METADATA
kakao_analyzer-1.0.2.dist-info/WHEEL
kakao_analyzer-1.0.2.dist-info/entry_points.txt
kakao_analyzer-1.0.2.dist-info/top_level.txt
kakao_analyzer-1.0.2.dist-info/RECORD
