Metadata-Version: 2.4
Name: kakao-analyzer
Version: 1.0.2
Summary: Comprehensive analysis tool for KakaoTalk chat exports
Home-page: https://github.com/xistoh162108/kakaotalk_analyzer
Author: xistoh162108, Claude AI
Author-email: xistoh162108@kaist.ac.kr
License: MIT
Project-URL: Bug Reports, https://github.com/xistoh162108/kakaotalk_analyzer/issues
Project-URL: Documentation, https://github.com/xistoh162108/kakaotalk_analyzer/blob/main/README.md
Project-URL: Source, https://github.com/xistoh162108/kakaotalk_analyzer
Keywords: kakao kakaotalk chat analysis nlp korean messaging
Classifier: Development Status :: 4 - Beta
Classifier: Intended Audience :: Science/Research
Classifier: Intended Audience :: Developers
Classifier: License :: OSI Approved :: MIT License
Classifier: Operating System :: OS Independent
Classifier: Programming Language :: Python :: 3
Classifier: Programming Language :: Python :: 3.8
Classifier: Programming Language :: Python :: 3.9
Classifier: Programming Language :: Python :: 3.10
Classifier: Programming Language :: Python :: 3.11
Classifier: Topic :: Communications :: Chat
Classifier: Topic :: Scientific/Engineering :: Information Analysis
Classifier: Topic :: Text Processing :: Linguistic
Requires-Python: >=3.8
License-File: LICENSE
Requires-Dist: pandas>=1.5.0
Requires-Dist: numpy>=1.21.0
Requires-Dist: matplotlib>=3.5.0
Requires-Dist: seaborn>=0.11.0
Requires-Dist: wordcloud>=1.8.0
Requires-Dist: scikit-learn>=1.1.0
Requires-Dist: sentence-transformers>=2.2.0
Requires-Dist: torch>=1.13.0
Requires-Dist: transformers>=4.21.0
Requires-Dist: chardet>=4.0.0
Requires-Dist: tqdm>=4.60.0
Requires-Dist: requests>=2.25.0
Provides-Extra: dev
Requires-Dist: pytest>=6.0; extra == "dev"
Requires-Dist: black>=21.0; extra == "dev"
Requires-Dist: flake8>=3.8; extra == "dev"
Provides-Extra: full
Requires-Dist: sentence-transformers>=2.0; extra == "full"
Requires-Dist: transformers>=4.0; extra == "full"
Requires-Dist: torch>=1.9; extra == "full"
Dynamic: author
Dynamic: author-email
Dynamic: classifier
Dynamic: description
Dynamic: description-content-type
Dynamic: home-page
Dynamic: keywords
Dynamic: license
Dynamic: license-file
Dynamic: project-url
Dynamic: provides-extra
Dynamic: requires-dist
Dynamic: requires-python
Dynamic: summary
